odoo8_addon_l10n_id_taxform_pph_21_payslip-8.0.1.0.0-py2.7-nspkg.pth
odoo_addons/l10n_id_taxform_pph_21_payslip/__openerp__.py
odoo_addons/l10n_id_taxform_pph_21_payslip/__init__.py
odoo_addons/l10n_id_taxform_pph_21_payslip/README.rst
odoo_addons/l10n_id_taxform_pph_21_payslip/models/hr_payslip.py
odoo_addons/l10n_id_taxform_pph_21_payslip/models/__init__.py
odoo_addons/l10n_id_taxform_pph_21_payslip/views/hr_payslip_views.xml
odoo_addons/l10n_id_taxform_pph_21_payslip/data/hr_salary_rule_category_data.xml
odoo_addons/l10n_id_taxform_pph_21_payslip/data/hr_salary_rule_data.xml
odoo_addons/l10n_id_taxform_pph_21_payslip/tests/test_compute_payslip_tax_period.py
odoo_addons/l10n_id_taxform_pph_21_payslip/tests/__init__.py
odoo_addons/l10n_id_taxform_pph_21_payslip/static/description/icon.png
odoo8_addon_l10n_id_taxform_pph_21_payslip-8.0.1.0.0.dist-info/top_level.txt
odoo8_addon_l10n_id_taxform_pph_21_payslip-8.0.1.0.0.dist-info/WHEEL
odoo8_addon_l10n_id_taxform_pph_21_payslip-8.0.1.0.0.dist-info/RECORD
odoo8_addon_l10n_id_taxform_pph_21_payslip-8.0.1.0.0.dist-info/metadata.json
odoo8_addon_l10n_id_taxform_pph_21_payslip-8.0.1.0.0.dist-info/DESCRIPTION.rst
odoo8_addon_l10n_id_taxform_pph_21_payslip-8.0.1.0.0.dist-info/METADATA
odoo8_addon_l10n_id_taxform_pph_21_payslip-8.0.1.0.0.dist-info/namespace_packages.txt
